junit_xml/__init__.py
junit_xml_2/__init__.py
junit_xml_2-1.9.dist-info/LICENSE.txt
junit_xml_2-1.9.dist-info/METADATA
junit_xml_2-1.9.dist-info/WHEEL
junit_xml_2-1.9.dist-info/top_level.txt
junit_xml_2-1.9.dist-info/RECORD
